magic_comic_reader/__init__.py
magic_comic_reader/magic_comic_reader.py
magic_comic_reader/reader.html
magic_comic_reader-1.8.dist-info/METADATA
magic_comic_reader-1.8.dist-info/RECORD
magic_comic_reader-1.8.dist-info/WHEEL
magic_comic_reader-1.8.dist-info/entry_points.txt
magic_comic_reader-1.8.dist-info/top_level.txt
