Metadata-Version: 2.1
Name: magic-comic-reader
Version: 1.8
Summary: Scrapes webcomics to make them easier to read.
Home-page: UNKNOWN
Author: David Nickerson
Author-email: UNKNOWN
License: Proprietary
Keywords: magic comic reader webcomic
Platform: UNKNOWN
Classifier: Development Status :: 4 - Beta
Classifier: Intended Audience :: End Users/Desktop
Classifier: License :: Other/Proprietary License
Classifier: Natural Language :: English
Classifier: Programming Language :: Python :: 3.6
Classifier: Topic :: Utilities
Requires-Python: >=3.6
Requires-Dist: lxml
